boolparse.py
boolparse-0.1.0.dist-info/METADATA
boolparse-0.1.0.dist-info/WHEEL
boolparse-0.1.0.dist-info/top_level.txt
boolparse-0.1.0.dist-info/RECORD
