Metadata-Version: 2.1
Name: boolparse
Version: 0.1.0
Summary: BoolParse is a lightweight library to evaluate boolean expressions
Home-page: https://github.com/josemvas/boolparse
License: LGPLv3+
Keywords: parser boolean expression
Platform: UNKNOWN
Classifier: Programming Language :: Python :: 3 :: Only
Classifier: License :: OSI Approved :: GNU Lesser General Public License v3 or later (LGPLv3+)
Classifier: Operating System :: POSIX
Requires-Python: >=3.6
